kicad_backannotate/__init__.py
kicad_backannotate/board_remap.py
kicad_backannotate/kicad_compat.py
kicad_backannotate/sch.py
kicad_backannotate/schematic_updater.py
kicad_backannotate/doc/__init__.py
kicad_backannotate/doc/generate_screenshots.py
kicad_backannotate/gui/Ui_main.py
kicad_backannotate/gui/__init__.py
kicad_backannotate/gui/kicad_backannotate_gui.py
kicad_backannotate/gui/main.py
kicad_backannotate/gui/model.py
kicad_backannotate/gui/ui_main.py
kicad_backannotate/test/__init__.py
kicad_backannotate/test/test_boardremap.py
kicad_backannotate/test/test_schematicupdate.py
kicad_backannotate-0.0.1.dist-info/DESCRIPTION.rst
kicad_backannotate-0.0.1.dist-info/METADATA
kicad_backannotate-0.0.1.dist-info/RECORD
kicad_backannotate-0.0.1.dist-info/WHEEL
kicad_backannotate-0.0.1.dist-info/entry_points.txt
kicad_backannotate-0.0.1.dist-info/metadata.json
kicad_backannotate-0.0.1.dist-info/top_level.txt
