Metadata-Version: 2.0
Name: kicad-backannotate
Version: 0.0.1
Summary: A back-annotation tool for Kicad EDA
Home-page: https://github.com/weatherhead99/kicad_backannotate
Author: Dan Weatherill
Author-email: plasteredparrot@gmail.com
License: GPL-3.0-or-later
Platform: UNKNOWN
Classifier: Development Status :: 4 - Beta
Classifier: Environment :: X11 Applications :: Qt
Classifier: Environment :: Win32 (MS Windows)
Classifier: Environment :: MacOS X
Classifier: Intended Audience :: End Users/Desktop
Classifier: Intended Audience :: Manufacturing
Classifier: License :: OSI Approved :: GNU General Public License v3 or later (GPLv3+)
Classifier: Topic :: Scientific/Engineering :: Electronic Design Automation (EDA)
Classifier: Programming Language :: Python :: 2 :: Only
Requires-Python: <3
